scriptman/__init__.py
scriptman/__run__.py
scriptman/core/_logo.txt
scriptman/core/_scripts.py
scriptman/core/_summary.py
scriptman/core/_version.py
scriptman/core/cli/__init__.py
scriptman/core/cli/_api.py
scriptman/core/cli/_cleanup.py
scriptman/core/cli/_config.py
scriptman/core/cli/_general.py
scriptman/core/cli/_init.py
scriptman/core/cli/_parser.py
scriptman/core/cli/_project.py
scriptman/core/cli/_run.py
scriptman/core/cli/_shell.py
scriptman/core/config/__init__.py
scriptman/core/config/_defaults.py
scriptman/core/config/_file_handler.py
scriptman/core/config/_manager.py
scriptman/core/config/_store.py
scriptman/core/config/_toml.py
scriptman/docs/powers/etl/ETL_API_Reference.md
scriptman/docs/powers/etl/ETL_Architecture.md
scriptman/docs/powers/etl/ETL_Examples.md
scriptman/docs/powers/etl/ETL_README.md
scriptman/docs/README.md
scriptman/powers/api/__init__.py
scriptman/powers/api/_exceptions.py
scriptman/powers/api/_handlers.py
scriptman/powers/api/_manager.py
scriptman/powers/api/_middleware.py
scriptman/powers/api/_models.py
scriptman/powers/api/_templates.py
scriptman/powers/cache/__init__.py
scriptman/powers/cache/_backend.py
scriptman/powers/cache/_diskcache.py
scriptman/powers/cleanup.py
scriptman/powers/database/__init__.py
scriptman/powers/database/_database.py
scriptman/powers/database/_exceptions.py
scriptman/powers/database/_pyodbc.py
scriptman/powers/database/_sqlalchemy.py
scriptman/powers/etl/__init__.py
scriptman/powers/etl/_database.py
scriptman/powers/etl/_queue.py
scriptman/powers/generics.py
scriptman/powers/retry.py
scriptman/powers/scheduler/__init__.py
scriptman/powers/scheduler/api.py
scriptman/powers/scheduler/host.py
scriptman/powers/scheduler/models.py
scriptman/powers/scheduler/service.py
scriptman/powers/scheduler/triggers.py
scriptman/powers/selenium/__init__.py
scriptman/powers/selenium/_chrome.py
scriptman/powers/selenium/_firefox.py
scriptman/powers/selenium/_utils.py
scriptman/powers/serializer.py
scriptman-2.9.584.dist-info/entry_points.txt
scriptman-2.9.584.dist-info/licenses/LICENSE
scriptman-2.9.584.dist-info/METADATA
scriptman-2.9.584.dist-info/WHEEL
scriptman-2.9.584.dist-info/RECORD
