Metadata-Version: 2.4
Name: scriptman
Version: 2.9.584
Summary: A powerful Python package for automation, script management, and workflow orchestration.
License: MIT License
License-File: LICENSE
Author: Nelson Ombuya
Author-email: developer@incognitouser.anonaddy.me
Requires-Python: >=3.12,<4.0
Classifier: License :: OSI Approved :: MIT License
Provides-Extra: api
Provides-Extra: cache
Provides-Extra: etl
Provides-Extra: pyodbc
Provides-Extra: selenium
Provides-Extra: sqlalchemy
Requires-Dist: dill (>=0.3.9) ; extra == "cache"
Requires-Dist: diskcache (>=5.6.3) ; extra == "cache"
Requires-Dist: fastapi (>=0.115.12) ; extra == "api"
Requires-Dist: filelock (>=3.16.1)
Requires-Dist: loguru (>=0.7.3)
Requires-Dist: pandas (>=2.2.3) ; extra == "etl"
Requires-Dist: pandas-stubs (>=2.2.3.241126) ; extra == "etl"
Requires-Dist: psutil (>=7.0.0,<8.0.0)
Requires-Dist: pydantic[email] (>=2.10.6) ; extra == "api"
Requires-Dist: pyodbc (>=5.2.0) ; extra == "pyodbc"
Requires-Dist: pyodbc (>=5.2.0) ; extra == "sqlalchemy"
Requires-Dist: requests (>=2.32.3) ; extra == "api"
Requires-Dist: requests (>=2.32.3) ; extra == "selenium"
Requires-Dist: selenium (>=4.28.1) ; extra == "selenium"
Requires-Dist: sqlalchemy (>=2.0.37) ; extra == "sqlalchemy"
Requires-Dist: tomlkit (>=0.13.2)
Requires-Dist: tqdm (>=4.67.1)
Requires-Dist: types-psutil (>=7.0.0.20250601,<8.0.0.0)
Requires-Dist: types-requests (>=2.32.0.20241016) ; extra == "api"
Requires-Dist: types-requests (>=2.32.0.20241016) ; extra == "selenium"
Requires-Dist: types-selenium (>=3.141.9) ; extra == "selenium"
Requires-Dist: types-tqdm (>=4.67.0.20241221)
Requires-Dist: uvicorn (>=0.34.0) ; extra == "api"
Requires-Dist: webdriver-manager (>=4.0.2) ; extra == "selenium"
